llmbox/__init__.py
llmbox/chat/__init__.py
llmbox/chat/chat.py
llmbox/llms/__init__.py
llmbox/llms/anthropic.py
llmbox/llms/base.py
llmbox/llms/claude.py
llmbox/llms/gpt.py
llmbox-0.3.1.dist-info/LICENSE
llmbox-0.3.1.dist-info/METADATA
llmbox-0.3.1.dist-info/WHEEL
llmbox-0.3.1.dist-info/top_level.txt
llmbox-0.3.1.dist-info/RECORD
