Metadata-Version: 2.1
Name: llmbox
Version: 0.3.1
Summary: LLMs at your service
Home-page: https://github.com/victorycrest/llmbox
Author: Victory Crest
Author-email: victorycrest1602@gmail.com
License: Apache License, Version 2.0
Project-URL: Source, https://github.com/victorycrest/llmbox
Project-URL: Tracker, https://github.com/victorycrest/llmbox/issues
Keywords: artificial intelligence,large language model,llm,machine learning,nocode
Platform: any
Classifier: Programming Language :: Python :: 3.11
Classifier: Programming Language :: Python :: 3.10
Classifier: License :: OSI Approved :: Apache Software License
Classifier: Operating System :: OS Independent
Requires-Python: >=3.10
License-File: LICENSE
Requires-Dist: anthropic
Requires-Dist: openai
